pyjuliusalign/__init__.py
pyjuliusalign/alignFromTextgrid.py
pyjuliusalign/audioScripts.py
pyjuliusalign/convertKana.py
pyjuliusalign/hiraganaChart.txt
pyjuliusalign/jProcessingSnippet.py
pyjuliusalign/juliusAlignment.py
pyjuliusalign/julius_to_p2fa.py
pyjuliusalign/katakanaChart.txt
pyjuliusalign/unidic.py
pyjuliusalign/utils.py
pyjuliusalign/yomi2voca.py
pyjuliusalign-4.0.0.dist-info/LICENSE
pyjuliusalign-4.0.0.dist-info/METADATA
pyjuliusalign-4.0.0.dist-info/WHEEL
pyjuliusalign-4.0.0.dist-info/top_level.txt
pyjuliusalign-4.0.0.dist-info/RECORD
