Metadata-Version: 2.1
Name: pyjuliusalign
Version: 4.0.0
Summary: A helper library for doing forced-alignment in Japanese with Julius.
Home-page: https://github.com/timmahrt/pyJuliusAlign
Author: Tim Mahrt
Author-email: timmahrt@gmail.com
License: LICENSE
Platform: UNKNOWN
Requires-Python: >3.6.0
License-File: LICENSE
Requires-Dist: praatio (~=6.0)
Requires-Dist: python-Levenshtein
Requires-Dist: pydub
Requires-Dist: typing-extensions
